{
  "lastRun": "2026-04-24T11:04:14.770102+00:00",
  "symbols": [
    "GLD",
    "USO",
    "BNO",
    "CORN",
    "WEAT",
    "SOYB",
    "PDBC",
    "SPY",
    "QQQ",
    "DIA",
    "IWM",
    "VTI",
    "EEM",
    "TLT",
    "XLF",
    "XLE",
    "XLK",
    "XLU",
    "XLP",
    "XLY",
    "XLI",
    "XLB",
    "XLRE",
    "ARKK",
    "ARKG",
    "GDX",
    "GDXJ",
    "ICLN",
    "BOTZ",
    "CIBR",
    "VNQ",
    "EFA",
    "EWJ",
    "EWZ",
    "FXI",
    "VGK",
    "EWT",
    "SCHD",
    "VYM",
    "BND",
    "AGG",
    "TIP",
    "SHY",
    "MUB",
    "AAPL",
    "MSFT",
    "GOOGL",
    "AMZN",
    "NVDA",
    "META",
    "TSLA",
    "JPM",
    "V",
    "WMT",
    "PG",
    "MA",
    "HD",
    "PFE",
    "MRK",
    "ABBV",
    "LLY",
    "AVGO",
    "NFLX",
    "AMD",
    "INTC",
    "QCOM",
    "CRM",
    "NOW",
    "ADBE",
    "ORCL",
    "GS",
    "MS",
    "AXP",
    "BLK",
    "UNH",
    "AMGN",
    "GILD",
    "BA",
    "RTX",
    "DE",
    "GE",
    "DIS",
    "SBUX",
    "NKE",
    "MCD",
    "F",
    "T",
    "C",
    "WFC",
    "FXE",
    "FXB",
    "FXA",
    "FXC",
    "IBIT",
    "FBTC",
    "ETHA",
    "GBTC",
    "BITO",
    "MSTR",
    "COIN",
    "MARA"
  ],
  "count": 101,
  "failed": [
    "SLV",
    "UNG",
    "COPX",
    "HYG",
    "XLV",
    "INDA",
    "LQD",
    "IEF",
    "BLOK",
    "MOO",
    "BRK-B",
    "JNJ",
    "BAC",
    "XOM",
    "CVX",
    "KO",
    "COST",
    "LMT",
    "CAT",
    "HON",
    "GM",
    "VZ",
    "SCHW",
    "FXY",
    "UUP",
    "UDN",
    "RIOT"
  ],
  "success": 101,
  "skipped": 0
}